arepo/__init__.py
arepo/base.py
arepo/db.py
arepo/main.py
arepo/mixins.py
arepo/models/__init__.py
arepo/models/bf.py
arepo/models/data.py
arepo/models/source.py
arepo/models/common/__init__.py
arepo/models/common/reference.py
arepo/models/common/tag.py
arepo/models/common/vulnerability.py
arepo/models/common/weakness.py
arepo/models/common/platform/__init__.py
arepo/models/common/platform/configuration.py
arepo/models/common/platform/cpe.py
arepo/models/common/platform/product.py
arepo/models/common/platform/vendor.py
arepo/models/common/scoring/__init__.py
arepo/models/common/scoring/cvss2.py
arepo/models/common/scoring/cvss3.py
arepo/models/vcs/__init__.py
arepo/models/vcs/diff.py
arepo/models/vcs/symbol.py
arepo/models/vcs/core/__init__.py
arepo/models/vcs/core/commit.py
arepo/models/vcs/core/repository.py
arepo/tables/abstractions.csv
arepo/tables/bf_classes.csv
arepo/tables/cwe_class.csv
arepo/tables/cwe_operation.csv
arepo/tables/cwe_phase.csv
arepo/tables/cwes.csv
arepo/tables/groupings.csv
arepo/tables/operations.csv
arepo/tables/phases.csv
arepo/tables/tags.csv
arepo/tables/vendor_product_type.csv
arepo/utils/__init__.py
arepo/utils/db.py
arepo/utils/err.py
arepo/utils/misc.py
examples/source_divergence.py
examples/source_intersection.py
arepo-3.5.0.dist-info/METADATA
arepo-3.5.0.dist-info/WHEEL
arepo-3.5.0.dist-info/entry_points.txt
arepo-3.5.0.dist-info/top_level.txt
arepo-3.5.0.dist-info/RECORD
